[
      {
            "Id": 1,
            "ListName": "BMW",
            "DateCreated": "Feb 15, 2015.",
            "Members": "10200",
            "OptOuts": "125",
            "LastSent": "Feb 20 1:56 PM"
        },
        {
            "Id": 2,
            "ListName": "Mercedes",
            "DateCreated": "Feb 19, 2015.",
            "Members": "8400",
            "OptOuts": "15",
            "LastSent": "Feb 20 8:43 PM"
        },
        {
            "Id": 3,
            "ListName": "Nestle",
            "DateCreated": "Feb 11, 2015.",
            "Members": "2600",
            "OptOuts": "11",
            "LastSent": "Feb 22 2:56 PM"
        },
        {
            "Id": 4,
            "ListName": "Private",
            "DateCreated": "Feb 1, 2015.",
            "Members": "23",
            "OptOuts": "0",
            "LastSent": "Feb 25 3:59 PM"
        },
        {
            "Id": 5,
            "ListName": "Audi",
            "DateCreated": "Feb 6, 2015.",
            "Members": "987",
            "OptOuts": "88",
            "LastSent": "Feb 9 9:00 AM"
        }
      ]